FlaskOIDC/FlaskOIDC.py
FlaskOIDC/JWKS.py
FlaskOIDC/__init__.py
FlaskOIDC/flask_utils.py
FlaskOIDC/oidc_discover.py
FlaskOIDC/oidc_state.py
Flask_OIDC_SP-22.2.28.data/data/examples/app.py
Flask_OIDC_SP-22.2.28.data/data/examples/config_sample.py
Flask_OIDC_SP-22.2.28.data/scripts/example_flask_oidc_app.py
Flask_OIDC_SP-22.2.28.dist-info/LICENSE.txt
Flask_OIDC_SP-22.2.28.dist-info/METADATA
Flask_OIDC_SP-22.2.28.dist-info/WHEEL
Flask_OIDC_SP-22.2.28.dist-info/top_level.txt
Flask_OIDC_SP-22.2.28.dist-info/RECORD
