Metadata-Version: 2.1
Name: Flask-OIDC-SP
Version: 22.2.28
Summary: OIDC Service Provider for Flask applications
Home-page: https://github.com/Glocktober/FlaskOIDC
Author: gunville
Author-email: rk13088@yahoo.com
License: UNKNOWN
Project-URL: repo, https://github.com/Glocktober/FlaskOIDC
Project-URL: overview, https://github.com/Glocktober/FlaskOIDC/blob/master/README.md
Keywords: 'flask oidc authentication'
Platform: UNKNOWN
Classifier: Programming Language :: Python :: 3
Classifier: License :: OSI Approved :: MIT License
Classifier: Operating System :: OS Independent
Classifier: Framework :: Bottle
Requires-Python: >=3.6
License-File: LICENSE.txt
Requires-Dist: Flask (>=2.0.0)
Requires-Dist: Flask-Session (>=0.4.0)
Requires-Dist: PyJWT (>=2.1.0)
Requires-Dist: requests (>=2.26.0)
Requires-Dist: cryptography (>=3.0)
